<?xml version="1.0"?>
<!--
  ~ jPOS Project [http://jpos.org]
  ~ Copyright (C) 2000-2015 Alejandro P. Revilla
  ~
  ~ This program is free software: you can redistribute it and/or modify
  ~ it under the terms of the GNU Affero General Public License as
  ~ published by the Free Software Foundation, either version 3 of the
  ~ License, or (at your option) any later version.
  ~
  ~ This program is distributed in the hope that it will be useful,
  ~ but WITHOUT ANY WARRANTY; without even the implied warranty of
  ~ MERCHANTABILITY or FITNESS FOR A PARTICULAR PURPOSE.  See the
  ~ GNU Affero General Public License for more details.
  ~
  ~ You should have received a copy of the GNU Affero General Public License
  ~ along with this program.  If not, see <http://www.gnu.org/licenses/>.
  -->

<!DOCTYPE hibernate-mapping
  SYSTEM "http://www.hibernate.org/dtd/hibernate-mapping-3.0.dtd">

<hibernate-mapping>
  <class name="org.jpos.ee.Consumer" table="consumer">
    <id name="id" column="id" type="string">
      <generator class="assigned" />
    </id>
    <property name="hash" length="8000" type="string" />
    <property name="active" type="yes_no" />
    <property name="deleted" type="yes_no" />
    <property name="startDate"     type="date" />
    <property name="endDate"       type="date" />
    <many-to-one name="user"
                 class="org.jpos.ee.User"
                 column="eeuser"
                 foreign-key="FKConsumerUser" />

    <set name="roles" lazy="false" table="consumer_roles">
     <key column="consumer" foreign-key="FKConsumerRolesConsumer"/>
     <many-to-many column="role" class="org.jpos.ee.Role" foreign-key="FKConsumerRolesRole"/>
    </set>

    <map name="props" lazy="true" table="consumer_props" 
        cascade="all-delete-orphan">
        <key foreign-key="FKConsumerProps" />
        <index column="propName" type="string" length="64"/>
        <element column="propValue" type="string"/>
    </map>
    <fetch-profile name="eager">
        <fetch association="user" style="join"/>
    </fetch-profile>
  </class>
</hibernate-mapping>
